{
  "result": "0",
  "list": [
    {
      "title": "Big Wedding Day",
      "filePath": "http://ramedia.sinaapp.com/res/Video/BigWeddingDay.hlv",
      "thumbPath": "http://ramedia.sinaapp.com/res/Video/BigWeddingDay.png",
      "id": "2"
    },
    {
      "title": "Bright and Early",
      "filePath": "http://ramedia.sinaapp.com/res/Video/BrightandEarly.hlv",
      "thumbPath": "http://ramedia.sinaapp.com/res/Video/BrightandEarly.png",
      "id": "2"
    },
    {
      "title": "Get Back Together",
      "filePath": "http://ramedia.sinaapp.com/res/Video/GetBackTogether.hlv",
      "thumbPath": "http://ramedia.sinaapp.com/res/Video/GetBackTogether.png",
      "id": "2"
    },
    {
      "title": "Get Cold Feet",
      "filePath": "http://ramedia.sinaapp.com/res/Video/GetColdFeet.hlv",
      "thumbPath": "http://ramedia.sinaapp.com/res/Video/GetColdFeet.png",
      "id": "2"
    },
    {
      "title": "Get Over Somebody",
      "filePath": "http://ramedia.sinaapp.com/res/Video/GetOverSomebody.hlv",
      "thumbPath": "http://ramedia.sinaapp.com/res/Video/GetOverSomebody.png",
      "id": "2"
    },
    {
      "title": "Good for you",
      "filePath": "http://ramedia.sinaapp.com/res/Video/Goodforyou.hlv",
      "thumbPath": "http://ramedia.sinaapp.com/res/Video/Goodforyou.png",
      "id": "2"
    },
    {
      "title": "Marriage Proposal",
      "filePath": "http://ramedia.sinaapp.com/res/Video/MarriageProposal.hlv",
      "thumbPath": "http://ramedia.sinaapp.com/res/Video/MarriageProposal.png",
      "id": "2"
    },
    {
      "title": "Off the Beaten Path",
      "filePath": "http://ramedia.sinaapp.com/res/Video/OfftheBeatenPath.hlv",
      "thumbPath": "http://ramedia.sinaapp.com/res/Video/OfftheBeatenPath.png",
      "id": "2"
    },
    {
      "title": "Single and Ready to Mingle",
      "filePath": "http://ramedia.sinaapp.com/res/Video/SingleandReadytoMingle.hlv",
      "thumbPath": "http://ramedia.sinaapp.com/res/Video/SingleandReadytoMingle.png",
      "id": "2"
    },
    {
      "title": "Soul Mate",
      "filePath": "http://ramedia.sinaapp.com/res/Video/SoulMate.hlv",
      "thumbPath": "http://ramedia.sinaapp.com/res/Video/SoulMate.png",
      "id": "2"
    }
  ]
}